{
    "imageUrl": "http://aruodas-img.dgn.lt/object_26_30329751/nuotrauka.jpg",
    "url": "http://www.aruodas.lt/butai-kaune-centre-laisves-al-naujas-euroremontas-modernus-dizainas-1-2110395/",
    "ids": [
        "2110395"
    ],
    "address": "Kaunas, Centras, Laisvės al.",
    "rooms": 4,
    "area": 78,
    "floor": "3/5",
    "phones": [],
    "priceHistory": [
        {
            "date": "12/06/2016",
            "price": "78000",
            "url": "http://www.aruodas.lt/butai-kaune-centre-laisves-al-naujas-euroremontas-modernus-dizainas-1-2110395/"
        }
    ]
}
